zuzuvibhu/__init__.py
zuzuvibhu/get_zuzus.py
zuzuvibhu-1.0.4.dist-info/LICENSE
zuzuvibhu-1.0.4.dist-info/METADATA
zuzuvibhu-1.0.4.dist-info/WHEEL
zuzuvibhu-1.0.4.dist-info/top_level.txt
zuzuvibhu-1.0.4.dist-info/RECORD
