Metadata-Version: 2.1
Name: zuzuvibhu
Version: 1.0.4
Summary: Zuzu Package of Vibhu Agarwal
Home-page: https://github.com/Vibhu-Agarwal/zuzuvibhu
Author: Vibhu Agarwal
Author-email: vibhu4agarwal@gmail.com
License: MIT
Keywords: zuzu vibhu agarwal vibhuagarwal
Platform: UNKNOWN
Classifier: Programming Language :: Python :: 3
Classifier: License :: OSI Approved :: MIT License
Classifier: Operating System :: OS Independent
Requires-Dist: Click (==7.0)
Requires-Dist: Flask (==1.0.2)
Requires-Dist: itsdangerous (==1.1.0)
Requires-Dist: Jinja2 (==2.10)
Requires-Dist: MarkupSafe (==1.1.0)
Requires-Dist: Werkzeug (==0.14.1)
